{"titles":{"en":"High School DxD","en_jp":"High School DxD","ja_jp":"High School DxD"},"synopsis":"High school student Issei Hyoudou is your run-of-the-mill pervert who does nothing productive with his life, peeping on women and dreaming of having his own harem one day. Things seem to be looking up for Issei when a beautiful girl asks him out on a date, although she turns out to be a fallen angel who brutally kills him! However, he gets a second chance at life when beautiful senior student Rias Gremory, who is a top-class devil, revives him as her servant, recruiting Issei into the ranks of the school's Occult Research club.\nSlowly adjusting to his new life, Issei must train and fight in order to survive in the violent world of angels and devils. Each new adventure leads to many hilarious (and risqué) moments with his new comrades, all the while keeping his new life a secret from his friends and family in High School DxD!\n[Written by MAL Rewrite]","started_airing_date":"2012-01-06","finished_airing_date":"2012-03-23","cover_image":{"tiny":"https://media.kitsu.io/anime/cover_images/6550/tiny.jpg?1422198596","small":"https://media.kitsu.io/anime/cover_images/6550/small.jpg?1422198596","medium":"","large":"https://media.kitsu.io/anime/cover_images/6550/large.jpg?1422198596"},"poster_image":{"tiny":"https://media.kitsu.io/anime/poster_images/6550/tiny.jpg?1417468903","small":"https://media.kitsu.io/anime/poster_images/6550/small.jpg?1417468903","medium":"https://media.kitsu.io/anime/poster_images/6550/medium.jpg?1417468903","large":"https://media.kitsu.io/anime/poster_images/6550/large.jpg?1417468903"},"genres":[],"age_rating":"R","episode_count":12,"community_rating":3.7295,"entries":[],"smartentries":[{"data":["http://www.animeplus.tv/high-school-dxd-episode-",0,"-online"],"start":1,"end":12},{"data":["http://ww2.chia-anime.tv/high-school-dxd-new-episode-",0,"-english-subbed/"],"start":1,"end":12},{"data":["http://www.masterani.me/anime/watch/223-high-school-dxd/",0],"start":1,"end":12},{"data":["https://www2.gogoanime.se/high-school-dxd-episode-",0],"start":1,"end":12},{"data":["http://www.gogoanime.to/high-school-dxd-episode-",0],"start":1,"end":12}]}